{
  "KONU_TARAMA": {
    "10. Sınıf": {
      "Genel Muhasebe": {
        "Test 1 (Temel Kavramlar)": [
          {"soru": "İşletmenin varlık ve kaynaklarını gösteren tablo?", "secenekler": ["Bilanço", "Gelir Tablosu", "Mizan", "Yevmiye"], "cevap": "Bilanço"},
          {"soru": "100 Kasa hesabı hangi gruptadır?", "secenekler": ["Dönen Varlıklar", "Duran Varlıklar", "Kısa Vadeli Kaynaklar", "Öz Kaynaklar"], "cevap": "Dönen Varlıklar"},
          {"soru": "Satıcıya olan senetsiz borçlar?", "secenekler": ["320 Satıcılar", "120 Alıcılar", "100 Kasa", "321 Borç Senetleri"], "cevap": "320 Satıcılar"},
          {"soru": "Nazım Hesapların özelliği?", "secenekler": ["Bilgi amaçlıdır", "Borç bakiyesi verir", "Kârı gösterir", "Vergi hesaplar"], "cevap": "Bilgi amaçlıdır"},
          {"soru": "Tacir kime denir?", "secenekler": ["Ticari işletmeyi kendi adına işleten kişiye", "Müdüre", "Esnafa", "Memura"], "cevap": "Ticari işletmeyi kendi adına işleten kişiye"},
          {"soru": "Kasadan para çıkışı olunca kasa nasıl çalışır?", "secenekler": ["Alacaklandırılır", "Borçlandırılır", "Değişmez", "Kapatılır"], "cevap": "Alacaklandırılır"},
          {"soru": "102 Bankalar hesabı karakteri?", "secenekler": ["Aktif", "Pasif", "Düzenleyici", "Nazım"], "cevap": "Aktif"},
          {"soru": "Veresiye mal satışı kaydı?", "secenekler": ["120 Alıcılar", "320 Satıcılar", "100 Kasa", "600 Satışlar"], "cevap": "120 Alıcılar"},
          {"soru": "KDV hariç tutarı bulmak için (KDV %20)?", "secenekler": ["1,20'ye bölünür", "0,20 ile çarpılır", "1,18'e bölünür", "20 ile çarpılır"], "cevap": "1,20'ye bölünür"},
          {"soru": "İşletmenin kullandığı bilgisayar hangi hesap?", "secenekler": ["255 Demirbaşlar", "153 Ticari Mallar", "770 Gider", "254 Taşıtlar"], "cevap": "255 Demirbaşlar"},
          {"soru": "Çek keşide etmek?", "secenekler": ["Çek düzenleyip vermek", "Çek tahsil etmek", "Bankaya yatırmak", "Ciro etmek"], "cevap": "Çek düzenleyip vermek"},
          {"soru": "103 Verilen Çekler bilançoda nerede?", "secenekler": ["Dönen Varlıklar (-) olarak", "Pasif tarafta", "Gelir tablosunda", "Duran varlıkta"], "cevap": "Dönen Varlıklar (-) olarak"},
          {"soru": "Tek Düzen Hesap Planı kodu örneği?", "secenekler": ["100", "9999", "ABC", "10-A"], "cevap": "100"},
          {"soru": "Tutulması zorunlu olmayan defter?", "secenekler": ["Çek Defteri", "Yevmiye", "Kebir", "Envanter"], "cevap": "Çek Defteri"},
          {"soru": "Dönem karı hangi hesaba devredilir?", "secenekler": ["690 Dönem Karı Zararı", "100 Kasa", "500 Sermaye", "600 Satışlar"], "cevap": "690 Dönem Karı Zararı"}
        ],
        "Test 2 (Kasa ve Banka)": [
          {"soru": "Kasa noksanı geçici hesap?", "secenekler": ["197 Sayım Noksanları", "397 Sayım Fazlaları", "689 Gider", "100 Kasa"], "cevap": "197 Sayım Noksanları"},
          {"soru": "Kasa fazlası geçici hesap?", "secenekler": ["397 Sayım Fazlaları", "197 Sayım Noksanları", "679 Gelir", "100 Kasa"], "cevap": "397 Sayım Fazlaları"},
          {"soru": "Bankaya para yatırılması?", "secenekler": ["102 (B) / 100 (A)", "100 (B) / 102 (A)", "102 (B) / 120 (A)", "320 (B) / 100 (A)"], "cevap": "102 (B) / 100 (A)"},
          {"soru": "Bankadan para çekilmesi?", "secenekler": ["100 (B) / 102 (A)", "102 (B) / 100 (A)", "100 (B) / 120 (A)", "320 (B) / 102 (A)"], "cevap": "100 (B) / 102 (A)"},
          {"soru": "Alınan çek tahsili?", "secenekler": ["100 (B) / 101 (A)", "101 (B) / 100 (A)", "102 (B) / 100 (A)", "120 (B) / 101 (A)"], "cevap": "100 (B) / 101 (A)"},
          {"soru": "Ciro etmek ne demek?", "secenekler": ["Hakkını başkasına devretmek", "Tahsil etmek", "Bankaya yatırmak", "İptal etmek"], "cevap": "Hakkını başkasına devretmek"},
          {"soru": "Bloke çek nedir?", "secenekler": ["Karşılığı bankaca garanti edilen çek", "Karşılıksız çek", "Sahte çek", "Vadeli çek"], "cevap": "Karşılığı bankaca garanti edilen çek"},
          {"soru": "Kambiyo karı hesabı?", "secenekler": ["646 Kambiyo Karları", "656 Zarar", "600 Satış", "642 Faiz"], "cevap": "646 Kambiyo Karları"},
          {"soru": "Kambiyo zararı hesabı?", "secenekler": ["656 Kambiyo Zararları", "646 Kar", "659 Gider", "780 Gider"], "cevap": "656 Kambiyo Zararları"},
          {"soru": "Pos cihazı satış hesabı?", "secenekler": ["108 Diğer Hazır Değerler", "100 Kasa", "102 Banka", "120 Alıcı"], "cevap": "108 Diğer Hazır Değerler"},
          {"soru": "Bankadaki paraya faiz işlemesi?", "secenekler": ["102 (B) / 642 (A)", "100 (B) / 642 (A)", "642 (B) / 102 (A)", "102 (B) / 600 (A)"], "cevap": "102 (B) / 642 (A)"},
          {"soru": "Verilen çekin ödenmesi?", "secenekler": ["103 (B) / 102 (A)", "102 (B) / 103 (A)", "320 (B) / 100 (A)", "100 (B) / 103 (A)"], "cevap": "103 (B) / 102 (A)"},
          {"soru": "Tahsil için bankaya çek verilmesi?", "secenekler": ["Nazım Hesaplarda izlenir", "102 (B)", "100 (B)", "120 (B)"], "cevap": "Nazım Hesaplarda izlenir"},
          {"soru": "Hatır çeki nedir?", "secenekler": ["Ticari işlem olmadan verilen çek", "Mal karşılığı", "Hizmet karşılığı", "Banka çeki"], "cevap": "Ticari işlem olmadan verilen çek"},
          {"soru": "Çekte vade var mıdır?", "secenekler": ["Hukuken yoktur, görüldüğünde ödenir", "Vardır", "1 aydır", "3 aydır"], "cevap": "Hukuken yoktur, görüldüğünde ödenir"}
        ],
        "Test 3 (Stoklar)": [{"soru": "Ana stok hesabı?", "secenekler": ["153 Ticari Mallar", "150", "151", "152"], "cevap": "153 Ticari Mallar"}],
        "Test 4 (Duran Varlıklar)": [{"soru": "Demirbaş hesabı?", "secenekler": ["255", "254", "252", "250"], "cevap": "255"}],
        "Test 5 (Gelir Tablosu)": [{"soru": "Satışlar hesabı?", "secenekler": ["600", "601", "602", "649"], "cevap": "600"}]
      },
      "Ekonomi": {
        "Test 1 (Temel Kavramlar)": [
          {"soru": "İnsan ihtiyaçlarını karşılayan araçlara ne denir?", "secenekler": ["Mal ve Hizmet", "Para", "Sermaye", "Emek"], "cevap": "Mal ve Hizmet"},
          {"soru": "Fayda nedir?", "secenekler": ["Malın ihtiyacı giderme özelliği", "Malın fiyatı", "Malın maliyeti", "Malın miktarı"], "cevap": "Malın ihtiyacı giderme özelliği"},
          {"soru": "Aşağıdakilerden hangisi üretim faktörüdür?", "secenekler": ["Emek", "Para", "Banka", "Döviz"], "cevap": "Emek"},
          {"soru": "Girişimci kime denir?", "secenekler": ["Üretim faktörlerini bir araya getiren kişi", "İşçi", "Memur", "Tüketici"], "cevap": "Üretim faktörlerini bir araya getiren kişi"},
          {"soru": "İhtiyaçlar nasıldır?", "secenekler": ["Sınırsızdır", "Sınırlıdır", "Sabittir", "Azalır"], "cevap": "Sınırsızdır"},
          {"soru": "Ekonomik mal nedir?", "secenekler": ["Elde etmek için emek ve bedel ödenen mal", "Hava", "Güneş ışığı", "Deniz suyu"], "cevap": "Elde etmek için emek ve bedel ödenen mal"},
          {"soru": "Tüketim nedir?", "secenekler": ["Mal ve hizmetlerin ihtiyaçları karşılamak için kullanılması", "Üretim", "Satış", "İhracat"], "cevap": "Mal ve hizmetlerin ihtiyaçları karşılamak için kullanılması"},
          {"soru": "Hizmet nedir?", "secenekler": ["Maddi olmayan ekonomik faaliyetler (Eğitim, Sağlık)", "Eşya", "Araba", "Ekmek"], "cevap": "Maddi olmayan ekonomik faaliyetler (Eğitim, Sağlık)"},
          {"soru": "Fayda çeşitlerinden 'Şekil Faydası' nedir?", "secenekler": ["Maddenin şeklinin değiştirilerek yararlı hale getirilmesi (Odun -> Masa)", "Yer değiştirme", "Zamanlama", "Mülkiyet"], "cevap": "Maddenin şeklinin değiştirilerek yararlı hale getirilmesi (Odun -> Masa)"},
          {"soru": "Ekonominin tanımı?", "secenekler": ["Sınırsız ihtiyaçların sınırlı kaynaklarla karşılanması bilimi", "Para sayma", "Banka yönetimi", "Ticaret"], "cevap": "Sınırsız ihtiyaçların sınırlı kaynaklarla karşılanması bilimi"},
          {"soru": "Mikro ekonomi neyi inceler?", "secenekler": ["Birey ve firma davranışlarını", "Devleti", "Dünyayı", "Enflasyonu"], "cevap": "Birey ve firma davranışlarını"},
          {"soru": "Makro ekonomi neyi inceler?", "secenekler": ["Milli gelir, enflasyon, işsizlik gibi genel konuları", "Bir fabrikayı", "Bir aileyi", "Bir bakkalı"], "cevap": "Milli gelir, enflasyon, işsizlik gibi genel konuları"},
          {"soru": "Serbest piyasa ekonomisi?", "secenekler": ["Fiyatların arz ve talebe göre belirlendiği sistem", "Devlet kontrolü", "Tekel", "Takas"], "cevap": "Fiyatların arz ve talebe göre belirlendiği sistem"},
          {"soru": "Enflasyon nedir?", "secenekler": ["Fiyatlar genel düzeyinin sürekli artışı", "Fiyat düşüşü", "Para basma", "Zenginleşme"], "cevap": "Fiyatlar genel düzeyinin sürekli artışı"},
          {"soru": "Deflasyon nedir?", "secenekler": ["Fiyatlar genel düzeyinin sürekli düşüşü", "Fiyat artışı", "Pahalılık", "Büyüme"], "cevap": "Fiyatlar genel düzeyinin sürekli düşüşü"}
        ],
        "Test 2 (Arz ve Talep)": [{"soru": "Fiyat artarsa talep ne olur?", "secenekler": ["Azalır", "Artar", "Değişmez", "Sıfırlanır"], "cevap": "Azalır"}],
        "Test 3 (Piyasalar)": [{"soru": "Tek satıcı?", "secenekler": ["Monopol", "Oligopol", "Tam Rekabet", "Düopol"], "cevap": "Monopol"}],
        "Test 4 (Para)": [{"soru": "Paranın işlevi?", "secenekler": ["Değişim aracı, değer ölçüsü", "Sadece kağıt", "Sadece maden", "Yatırım"], "cevap": "Değişim aracı, değer ölçüsü"}],
        "Test 5 (Milli Gelir)": [{"soru": "GSYİH?", "secenekler": ["Yurtiçi toplam üretim", "Dış borç", "İhracat", "İthalat"], "cevap": "Yurtiçi toplam üretim"}]
      },
      "Temel Hukuk": {
        "Test 1 (Hukuk Kuralları)": [
          {"soru": "Yaptırımı manevi olan kural?", "secenekler": ["Ahlak Kuralı", "Hukuk Kuralı", "Kanun", "Yönetmelik"], "cevap": "Ahlak Kuralı"},
          {"soru": "Hukuk kurallarının yaptırımı nasıldır?", "secenekler": ["Maddi ve Devlet gücüne dayalı", "Manevi", "Kınama", "Ayıplama"], "cevap": "Maddi ve Devlet gücüne dayalı"},
          {"soru": "Cebri icra nedir?", "secenekler": ["Borcunu ödemeyenin devlet zoruyla ödemesinin sağlanması", "Hapis", "Sürgün", "İdam"], "cevap": "Borcunu ödemeyenin devlet zoruyla ödemesinin sağlanması"},
          {"soru": "Tazminat nedir?", "secenekler": ["Verilen zararın ödetilmesi", "Cezaevi", "Hapis", "İptal"], "cevap": "Verilen zararın ödetilmesi"},
          {"soru": "Hükümsüzlük türlerinden 'Yokluk' nedir?", "secenekler": ["Kurucu unsurun eksik olması (İmam nikahı gibi)", "Kanuna aykırılık", "İrade sakatlığı", "Hata"], "cevap": "Kurucu unsurun eksik olması (İmam nikahı gibi)"},
          {"soru": "Mutlak butlan nedir?", "secenekler": ["İşlemin baştan itibaren geçersiz olması (Akıl hastasının evliliği)", "Sonradan iptal", "Geçerli işlem", "Yokluk"], "cevap": "İşlemin baştan itibaren geçersiz olması (Akıl hastasının evliliği)"},
          {"soru": "Nisbi butlan (İptal edilebilirlik) nedir?", "secenekler": ["İrade sakatlığı (Hata, hile, tehdit) ile yapılan işlem", "Yok hükmünde", "Kesin geçersiz", "Tam geçerli"], "cevap": "İrade sakatlığı (Hata, hile, tehdit) ile yapılan işlem"},
          {"soru": "Normlar hiyerarşisinin en üstü?", "secenekler": ["Anayasa", "Kanun", "Yönetmelik", "Genelge"], "cevap": "Anayasa"},
          {"soru": "Kanunları kim yapar?", "secenekler": ["TBMM", "Cumhurbaşkanı", "Mahkeme", "Vali"], "cevap": "TBMM"},
          {"soru": "Yönetmelik kim çıkarır?", "secenekler": ["Cumhurbaşkanı, Bakanlıklar ve Kamu Tüzel Kişileri", "Sadece meclis", "Muhtar", "Polis"], "cevap": "Cumhurbaşkanı, Bakanlıklar ve Kamu Tüzel Kişileri"},
          {"soru": "Örf ve adet hukuku nedir?", "secenekler": ["Yazısız hukuk kaynağı", "Kanun", "Kararname", "Tüzük"], "cevap": "Yazısız hukuk kaynağı"},
          {"soru": "Hakimin hukuk yaratması ne zaman olur?", "secenekler": ["Hukuk boşluğu varsa", "Kanun boşluğunda", "Her zaman", "Asla"], "cevap": "Hukuk boşluğu varsa"},
          {"soru": "Dürüstlük kuralı (Objektif iyi niyet) nerede geçerlidir?", "secenekler": ["Hakların kullanılmasında ve borçların ifasında", "Hak kazanırken", "Doğarken", "Ölürken"], "cevap": "Hakların kullanılmasında ve borçların ifasında"},
          {"soru": "İyiniyet (Subjektif) nerede geçerlidir?", "secenekler": ["Hakların kazanılmasında", "Hak kullanımında", "Borç ödemede", "Sözleşmede"], "cevap": "Hakların kazanılmasında"},
          {"soru": "Hakkın kötüye kullanılması?", "secenekler": ["Hukuk düzeni korumaz", "Korur", "Ceza vermez", "Ödüllendirir"], "cevap": "Hukuk düzeni korumaz"}
        ],
        "Test 2 (Kişiler Hukuku)": [{"soru": "Hak ehliyeti başlangıcı?", "secenekler": ["Sağ ve tam doğum", "18 yaş", "Evlilik", "Reşitlik"], "cevap": "Sağ ve tam doğum"}],
        "Test 3 (Aile Hukuku)": [{"soru": "Nişanlanma nedir?", "secenekler": ["Evlenme vaadi", "Evlilik", "Arkadaşlık", "Tanışma"], "cevap": "Evlenme vaadi"}],
        "Test 4 (Borçlar Hukuku)": [{"soru": "Sözleşme serbestisi?", "secenekler": ["İstenilen sözleşmeyi yapabilme", "Yasak", "Zorunluluk", "İzinli"], "cevap": "İstenilen sözleşmeyi yapabilme"}],
        "Test 5 (Anayasa)": [{"soru": "Yasama organı?", "secenekler": ["TBMM", "Cumhurbaşkanı", "Mahkeme", "Halk"], "cevap": "TBMM"}]
      }
    },
    "11. Sınıf": {
      "Şirketler Muhasebesi": {
        "Test 1 (Kuruluş İşlemleri)": [
          {"soru": "A.Ş. kuruluşunda nakit sermayenin en az ne kadarı peşin ödenmelidir?", "secenekler": ["%25 (1/4)", "%50", "Tamamı", "%10"], "cevap": "%25 (1/4)"},
          {"soru": "501 Ödenmemiş Sermaye hesabı bilançoda nerede ve nasıl yer alır?", "secenekler": ["Öz Kaynaklar grubunda eksi (-) değerle (Pasifi düzenleyen aktif)", "Aktifte", "Borçlarda", "Giderlerde"], "cevap": "Öz Kaynaklar grubunda eksi (-) değerle (Pasifi düzenleyen aktif)"},
          {"soru": "Limited Şirket hisse devri için hangi şart zorunludur?", "secenekler": ["Noter onayı ve Genel Kurul onayı", "Sadece sözlü anlaşma", "Banka dekontu", "Yönetim kurulu kararı"], "cevap": "Noter onayı ve Genel Kurul onayı"},
          {"soru": "Sermaye taahhüdü kaydında borçlu hesap hangisidir?", "secenekler": ["501 Ödenmemiş Sermaye", "500 Sermaye", "100 Kasa", "102 Bankalar"], "cevap": "501 Ödenmemiş Sermaye"},
          {"soru": "Ayni sermaye (Mal, Taşıt vb.) konulursa değerini kim belirler?", "secenekler": ["Mahkemece atanan Bilirkişi", "Ortaklar", "Noter", "Banka"], "cevap": "Mahkemece atanan Bilirkişi"},
          {"soru": "Hisse Senedi İhraç Primi (Agio) hangi hesapta izlenir?", "secenekler": ["520 Hisse Senedi İhraç Primleri", "500 Sermaye", "600 Satışlar", "649 Diğer Gelir"], "cevap": "520 Hisse Senedi İhraç Primleri"},
          {"soru": "Kuruluş ve Örgütlenme Giderleri (262) en fazla kaç yılda itfa edilir (yok edilir)?", "secenekler": ["5 Yıl", "1 Yıl", "10 Yıl", "Süresiz"], "cevap": "5 Yıl"},
          {"soru": "A.Ş. en az sermaye tutarı (2024)?", "secenekler": ["250.000 TL", "50.000 TL", "100.000 TL", "10.000 TL"], "cevap": "250.000 TL"},
          {"soru": "Limited Şirket en az sermaye tutarı (2024)?", "secenekler": ["50.000 TL", "10.000 TL", "100.000 TL", "5.000 TL"], "cevap": "50.000 TL"},
          {"soru": "Yedek Akçeler hangi grupta yer alır?", "secenekler": ["54- Kar Yedekleri", "52- Sermaye Yedekleri", "50- Sermaye", "59- Dönem Karı"], "cevap": "54- Kar Yedekleri"},
          {"soru": "I. Tertip Yasal Yedek Akçe oranı nedir?", "secenekler": ["Net karın %5'i", "%10", "%20", "%1"], "cevap": "Net karın %5'i"},
          {"soru": "Kar dağıtımında öncelik hangisindedir?", "secenekler": ["Vergi ve Yasal Yükümlülükler", "Ortaklar", "Yedekler", "Yönetim Kurulu"], "cevap": "Vergi ve Yasal Yükümlülükler"},
          {"soru": "Geçmiş yıl zararları (580) kapatılmadan kar dağıtımı yapılabilir mi?", "secenekler": ["Hayır yapılamaz", "Evet yapılabilir", "Kısmen yapılır", "Yedeklerden yapılır"], "cevap": "Hayır yapılamaz"},
          {"soru": "Tasfiye dönemi ne zaman başlar?", "secenekler": ["Tasfiye kararının tescil ve ilanıyla", "Zarar edince", "Borçlanınca", "Yıl sonunda"], "cevap": "Tasfiye kararının tescil ve ilanıyla"},
          {"soru": "Tasfiye sonunda kalan para kime dağıtılır?", "secenekler": ["Payları oranında ortaklara", "Devlete", "Çalışanlara", "Hayır kurumlarına"], "cevap": "Payları oranında ortaklara"}
        ],
        "Test 2 (Kar Dağıtımı)": [{"soru": "Temettü nedir?", "secenekler": ["Kar payı", "Faiz", "Vergi", "Maaş"], "cevap": "Kar payı"}],
        "Test 3 (Sermaye Artırımı)": [{"soru": "Bedelli artırım?", "secenekler": ["Nakit girişli", "Yedeklerden", "Kardan", "Fonlardan"], "cevap": "Nakit girişli"}],
        "Test 4 (Şirket Türleri)": [{"soru": "Sermayesi paylara bölünmüş şirket?", "secenekler": ["Anonim Şirket", "Kolektif", "Adi", "Komandit"], "cevap": "Anonim Şirket"}],
        "Test 5 (Tasfiye)": [{"soru": "Tasfiye memuru?", "secenekler": ["Tasfiyeyi yürüten kişi", "Müdür", "Ortak", "Memur"], "cevap": "Tasfiyeyi yürüten kişi"}]
      },
      "Maliyet Muhasebesi": {
        "Test 1 (Gider Hesapları)": [
          {"soru": "710 Direkt İlk Madde ve Malzeme Gideri nedir?", "secenekler": ["Üretilen mamulün bünyesine giren ana madde gideridir", "Yardımcı madde", "İşçilik", "Kira"], "cevap": "Üretilen mamulün bünyesine giren ana madde gideridir"},
          {"soru": "720 Direkt İşçilik Gideri?", "secenekler": ["Üretimde bizzat çalışan işçilerin ücretleri", "Müdür maaşı", "Bekçi maaşı", "Satıcı primi"], "cevap": "Üretimde bizzat çalışan işçilerin ücretleri"},
          {"soru": "730 Genel Üretim Giderleri?", "secenekler": ["Üretimle ilgili olup direkt yüklenemeyen (Kira, Enerji, Amortisman) giderler", "Hammadde", "Direkt işçilik", "Satış gideri"], "cevap": "Üretimle ilgili olup direkt yüklenemeyen (Kira, Enerji, Amortisman) giderler"},
          {"soru": "750 Araştırma ve Geliştirme Giderleri?", "secenekler": ["Yeni ürün/teknoloji geliştirme harcamaları", "Reklam", "Finansman", "Yönetim"], "cevap": "Yeni ürün/teknoloji geliştirme harcamaları"},
          {"soru": "760 Pazarlama Satış ve Dağıtım Giderleri?", "secenekler": ["Ürünün satışı, reklamı, nakliyesi ile ilgili giderler", "Üretim", "Yönetim", "Finansman"], "cevap": "Ürünün satışı, reklamı, nakliyesi ile ilgili giderler"},
          {"soru": "770 Genel Yönetim Giderleri?", "secenekler": ["İşletmenin yönetimi, ofis, muhasebe, hukuk giderleri", "Fabrika gideri", "Satış gideri", "Faiz"], "cevap": "İşletmenin yönetimi, ofis, muhasebe, hukuk giderleri"},
          {"soru": "780 Finansman Giderleri?", "secenekler": ["Kredi faizleri, kur farkı zararları", "Kira", "Maaş", "Vergi"], "cevap": "Kredi faizleri, kur farkı zararları"},
          {"soru": "Yansıtma hesaplarının kodu ne ile biter?", "secenekler": ["1 (711, 721, 731...)", "0", "2", "9"], "cevap": "1 (711, 721, 731...)"},
          {"soru": "Fark hesaplarının kodu ne ile biter?", "secenekler": ["2 (712, 722...)", "0", "1", "3"], "cevap": "2 (712, 722...)"},
          {"soru": "7/B seçeneğinde giderler nasıl izlenir?", "secenekler": ["Gider Çeşitleri (790-797) hesabında", "Fonksiyonel", "Bölümsel", "Ürün bazlı"], "cevap": "Gider Çeşitleri (790-797) hesabında"},
          {"soru": "790 İlk Madde ve Malzeme Giderleri (7/B)?", "secenekler": ["Tüm malzeme giderleri (Üretim, Yönetim, Pazarlama)", "Sadece üretim", "Sadece yönetim", "Sadece satış"], "cevap": "Tüm malzeme giderleri (Üretim, Yönetim, Pazarlama)"},
          {"soru": "791 İşçi Ücret ve Giderleri (7/B)?", "secenekler": ["Tüm personel giderleri", "Sadece fabrika", "Sadece ofis", "Sadece müdür"], "cevap": "Tüm personel giderleri"},
          {"soru": "793 Dışarıdan Sağlanan Fayda ve Hizmetler?", "secenekler": ["Elektrik, Su, Gaz, Haberleşme, Bakım", "Malzeme", "Personel", "Vergi"], "cevap": "Elektrik, Su, Gaz, Haberleşme, Bakım"},
          {"soru": "794 Çeşitli Giderler?", "secenekler": ["Sigorta, Kira, Mahkeme giderleri", "Faiz", "Hammadde", "İşçilik"], "cevap": "Sigorta, Kira, Mahkeme giderleri"},
          {"soru": "Maliyet muhasebesi hangi raporu düzenler?", "secenekler": ["Satılan Mamul Maliyeti Tablosu", "Bilanço", "Nakit Akış", "Özkaynak Değişim"], "cevap": "Satılan Mamul Maliyeti Tablosu"}
        ],
        "Test 2 (Maliyet Akışı)": [{"soru": "Hammadde üretime verilince?", "secenekler": ["710 (B) / 150 (A)", "150 (B) / 710 (A)", "151 (B)", "152 (B)"], "cevap": "710 (B) / 150 (A)"}],
        "Test 3 (Sipariş Maliyeti)": [{"soru": "Özel üretimde kullanılan sistem?", "secenekler": ["Sipariş Maliyet Sistemi", "Safha Maliyet", "Standart", "Değişken"], "cevap": "Sipariş Maliyet Sistemi"}],
        "Test 4 (Safha Maliyeti)": [{"soru": "Seri üretimde kullanılan sistem?", "secenekler": ["Safha (Evre) Maliyet", "Sipariş", "Tahmini", "Standart"], "cevap": "Safha (Evre) Maliyet"}],
        "Test 5 (Maliyet Analizi)": [{"soru": "Sabit maliyet?", "secenekler": ["Üretimden bağımsız değişmeyen gider", "Değişken gider", "Hammadde", "Enerji"], "cevap": "Üretimden bağımsız değişmeyen gider"}]
      },
      "Bilgisayarlı Muhasebe": {
        "Test 1 (Fiş İşlemleri)": [
          {"soru": "Kasa çıkışı fişi?", "secenekler": ["Tediye Fişi", "Tahsil Fişi", "Mahsup Fişi", "Açılış Fişi"], "cevap": "Tediye Fişi"},
          {"soru": "Kasa girişi fişi?", "secenekler": ["Tahsil Fişi", "Tediye Fişi", "Mahsup Fişi", "Kapanış Fişi"], "cevap": "Tahsil Fişi"},
          {"soru": "Kasasız işlem fişi?", "secenekler": ["Mahsup Fişi", "Tahsil", "Tediye", "Özel"], "cevap": "Mahsup Fişi"},
          {"soru": "Açılış fişi tarihi?", "secenekler": ["01.01.XXXX", "31.12.XXXX", "Dönem ortası", "Her ay başı"], "cevap": "01.01.XXXX"},
          {"soru": "Luca Kaydet kısayolu?", "secenekler": ["F2", "F5", "F10", "ESC"], "cevap": "F2"},
          {"soru": "Fiş kopyalama?", "secenekler": ["F5", "F2", "F1", "F9"], "cevap": "F5"},
          {"soru": "Bakiye eşitleme?", "secenekler": ["F7", "F4", "F12", "Esc"], "cevap": "F7"},
          {"soru": "Satır silme?", "secenekler": ["Alt + F3", "Delete", "F9", "Backspace"], "cevap": "Alt + F3"},
          {"soru": "Hesap planı?", "secenekler": ["F10", "F1", "F5", "F2"], "cevap": "F10"},
          {"soru": "KDV mahsup fişi ne zaman?", "secenekler": ["Ay sonu", "Yıl sonu", "Her gün", "Fatura kesince"], "cevap": "Ay sonu"},
          {"soru": "Yansıtma fişi?", "secenekler": ["Giderleri gelir tablosuna aktarır", "KDV hesaplar", "Stok sayar", "Fiş siler"], "cevap": "Giderleri gelir tablosuna aktarır"},
          {"soru": "Mizan?", "secenekler": ["Hesap özet tablosu", "Bilanço", "Kar zarar", "Defter"], "cevap": "Hesap özet tablosu"},
          {"soru": "Muavin defter?", "secenekler": ["Hesap detay dökümü", "Özet", "Borç", "Alacak"], "cevap": "Hesap detay dökümü"},
          {"soru": "Personel modülü?", "secenekler": ["Bordro yapar", "Fiş girer", "Stok tutar", "Demirbaş izler"], "cevap": "Bordro yapar"},
          {"soru": "E-Defter gönderim süresi?", "secenekler": ["Takip eden 3. ay sonu", "Her ay başı", "Yıl sonu", "Anında"], "cevap": "Takip eden 3. ay sonu"}
        ],
        "Test 2 (Beyannameler)": [{"soru": "KDV beyannamesi?", "secenekler": ["Ayın 28. günü", "24. günü", "15. günü", "Son günü"], "cevap": "Ayın 28. günü"}],
        "Test 3 (E-Fatura)": [{"soru": "Temel fatura?", "secenekler": ["Reddedilemeyen fatura", "Ticari fatura", "Kağıt fatura", "Arşiv"], "cevap": "Reddedilemeyen fatura"}],
        "Test 4 (Dönem Sonu)": [{"soru": "Kapanış fişi?", "secenekler": ["Otomatik oluşur", "Elle girilir", "Yapılmaz", "Silinir"], "cevap": "Otomatik oluşur"}],
        "Test 5 (Sabit Kıymet)": [{"soru": "Amortisman?", "secenekler": ["Otomatik hesaplanır", "Elle yapılır", "Hesaplanmaz", "Tahmindir"], "cevap": "Otomatik hesaplanır"}]
      }
    },
    "12. Sınıf": {
      "Finansal Okuryazarlık": {
        "Test 1 (Bütçe ve Planlama)": [
          {"soru": "Gelir - Gider?", "secenekler": ["Tasarruf (veya Açık)", "Ciro", "Kar", "Maliyet"], "cevap": "Tasarruf (veya Açık)"},
          {"soru": "Gider kalemi?", "secenekler": ["Kira", "Maaş", "Faiz Geliri", "Prim"], "cevap": "Kira"},
          {"soru": "İhtiyaç nedir?", "secenekler": ["Zorunlu harcama", "İstek", "Lüks", "Tatil"], "cevap": "Zorunlu harcama"},
          {"soru": "Bütçe nedir?", "secenekler": ["Gelecek planı", "Geçmiş özeti", "Banka", "Borç"], "cevap": "Gelecek planı"},
          {"soru": "Acil durum fonu?", "secenekler": ["Beklenmedik giderler için", "Tatil", "Araba", "Yatırım"], "cevap": "Beklenmedik giderler için"},
          {"soru": "Enflasyondan korunma?", "secenekler": ["Yatırım yapma", "Para saklama", "Harcama", "Borçlanma"], "cevap": "Yatırım yapma"},
          {"soru": "Risk - Getiri?", "secenekler": ["Doğru orantılı", "Ters orantılı", "İlişkisiz", "Risk kötüdür"], "cevap": "Doğru orantılı"},
          {"soru": "Portföy?", "secenekler": ["Yatırım çeşitlendirme", "Tek hisse", "Nakit", "Borç"], "cevap": "Yatırım çeşitlendirme"},
          {"soru": "Bileşik faiz?", "secenekler": ["Faizin faizi", "Basit faiz", "Düşük faiz", "Sabit faiz"], "cevap": "Faizin faizi"},
          {"soru": "Kredi notu?", "secenekler": ["Ödeme alışkanlığı puanı", "Gelir", "Zenginlik", "Eğitim"], "cevap": "Ödeme alışkanlığı puanı"},
          {"soru": "Asgari ödeme?", "secenekler": ["Kredi kartı minimum ödemesi", "Tamamı", "Faiz", "Aidat"], "cevap": "Kredi kartı minimum ödemesi"},
          {"soru": "BES?", "secenekler": ["Bireysel Emeklilik", "Banka", "Borsa", "Borç"], "cevap": "Bireysel Emeklilik"},
          {"soru": "DASK?", "secenekler": ["Zorunlu Deprem Sigortası", "Kasko", "Sağlık", "Hayat"], "cevap": "Zorunlu Deprem Sigortası"},
          {"soru": "Hisse senedi?", "secenekler": ["Ortaklık payı", "Borç senedi", "Faiz", "Döviz"], "cevap": "Ortaklık payı"},
          {"soru": "Tahvil?", "secenekler": ["Borçlanma senedi", "Ortaklık", "Hisse", "Tapu"], "cevap": "Borçlanma senedi"}
        ],
        "Test 2 (Yatırım)": [{"soru": "Altın?", "secenekler": ["Güvenli liman", "Riskli", "Spekülatif", "Değersiz"], "cevap": "Güvenli liman"}],
        "Test 3 (Bankacılık)": [{"soru": "Mevduat garantisi?", "secenekler": ["650.000 TL", "100.000 TL", "Sınırsız", "Yok"], "cevap": "650.000 TL"}],
        "Test 4 (Vergi)": [{"soru": "KDV?", "secenekler": ["Harcama vergisi", "Gelir vergisi", "Emlak vergisi", "Motorlu taşıt"], "cevap": "Harcama vergisi"}],
        "Test 5 (Sigorta)": [{"soru": "Trafik sigortası?", "secenekler": ["Zorunlu", "İsteğe bağlı", "Kasko", "Gereksiz"], "cevap": "Zorunlu"}]
      },
      "Bankacılık ve Banka Muhasebesi": {
        "Test 1 (Banka Tanımı ve İşlemler)": [
          {"soru": "Para basan kurum?", "secenekler": ["TCMB", "Ziraat", "Hazine", "Cumhurbaşkanı"], "cevap": "TCMB"},
          {"soru": "Mevduat nedir?", "secenekler": ["Bankaya yatan para", "Kredi", "Senet", "Faiz"], "cevap": "Bankaya yatan para"},
          {"soru": "Katılım bankası?", "secenekler": ["Faizsiz bankacılık", "Faizli", "Döviz bürosu", "Devlet bankası"], "cevap": "Faizsiz bankacılık"},
          {"soru": "Dekont?", "secenekler": ["İşlem belgesi", "Fatura", "Çek", "Senet"], "cevap": "İşlem belgesi"},
          {"soru": "IBAN?", "secenekler": ["26 hane", "24 hane", "16 hane", "11 hane"], "cevap": "26 hane"},
          {"soru": "EFT?", "secenekler": ["Farklı bankalar arası transfer", "Aynı banka", "Yurtdışı", "Nakit"], "cevap": "Farklı bankalar arası transfer"},
          {"soru": "Havale?", "secenekler": ["Aynı banka içi transfer", "Farklı banka", "Yurtdışı", "Çek"], "cevap": "Aynı banka içi transfer"},
          {"soru": "FAST?", "secenekler": ["7/24 Anlık transfer", "EFT", "Havale", "Swift"], "cevap": "7/24 Anlık transfer"},
          {"soru": "Kredi nedir?", "secenekler": ["Ödünç para verme", "Hibe", "Mevduat", "Yatırım"], "cevap": "Ödünç para verme"},
          {"soru": "Mevduat banka için nedir?", "secenekler": ["Borç (Pasif)", "Varlık", "Gelir", "Gider"], "cevap": "Borç (Pasif)"},
          {"soru": "Kredi banka için nedir?", "secenekler": ["Alacak (Aktif)", "Borç", "Sermaye", "Gider"], "cevap": "Alacak (Aktif)"},
          {"soru": "Teminat mektubu?", "secenekler": ["Gayrinakdi kredi", "Nakdi kredi", "Mevduat", "Para"], "cevap": "Gayrinakdi kredi"},
          {"soru": "Döviz alış kuru?", "secenekler": ["Bankanın döviz aldığı fiyat", "Sattığı fiyat", "Merkez kuru", "Borsa"], "cevap": "Bankanın döviz aldığı fiyat"},
          {"soru": "Kambiyo karı?", "secenekler": ["Döviz işlem karı", "Faiz", "Komisyon", "Hizmet"], "cevap": "Döviz işlem karı"},
          {"soru": "Stopaj?", "secenekler": ["Vergi kesintisi", "Faiz", "Komisyon", "Ücret"], "cevap": "Vergi kesintisi"}
        ],
        "Test 2 (Krediler)": [{"soru": "İhtiyaç kredisi?", "secenekler": ["Bireysel kredi", "Ticari", "Kurumsal", "Devlet"], "cevap": "Bireysel kredi"}],
        "Test 3 (Dış Ticaret)": [{"soru": "Akreditif?", "secenekler": ["Ödeme garantisi", "Nakit", "Çek", "Senet"], "cevap": "Ödeme garantisi"}],
        "Test 4 (Merkez Bankası)": [{"soru": "TCMB amacı?", "secenekler": ["Fiyat istikrarı", "Kar", "Kredi", "İstihdam"], "cevap": "Fiyat istikrarı"}],
        "Test 5 (Risk)": [{"soru": "KKB?", "secenekler": ["Kredi Kayıt Bürosu", "Merkez Bankası", "Maliye", "Tapu"], "cevap": "Kredi Kayıt Bürosu"}]
      }
    }
  },
  "DENEME_SINAVLARI": {
    "10. Sınıf Muhasebe": {
      "Deneme 1 (Genel Muhasebe)": [
        {"soru": "İşletmenin sahip olduğu varlıkların, işletme sahiplerinden ayrı olduğunu ifade eden kavram?", "secenekler": ["Kişilik", "Süreklilik", "Dönemsellik", "Maliyet Esası"], "cevap": "Kişilik"},
        {"soru": "Bilanço nedir?", "secenekler": ["İşletmenin belli bir tarihteki mali durum tablosu", "Kar zarar tablosu", "Nakit akış tablosu", "Maliyet tablosu"], "cevap": "İşletmenin belli bir tarihteki mali durum tablosu"}
      ]
    },
    "11. Sınıf Muhasebe": {
      "Deneme 1 (Maliyet & Şirketler)": [
        {"soru": "Kısa vadeli banka kredisi?", "secenekler": ["300 Banka Kredileri", "400 Kredi", "303 Taksit", "102 Banka"], "cevap": "300 Banka Kredileri"}
      ]
    },
    "12. Sınıf Muhasebe": {
      "Deneme 1 (Finans & Banka)": [
        {"soru": "Vadesi 1 yılın altına düşen uzun vadeli borç?", "secenekler": ["303 Uzun Vadeli Kredi Taksit", "300 Kredi", "400 Kredi", "304 Tahvil"], "cevap": "303 Uzun Vadeli Kredi Taksit"}
      ]
    }
  }
}
